fulladder.v
module full_adder (output sum, cout, input a, b, cin);
   wire temp_sum;
   assign temp_sum = a^b;
   assign sum = temp_sum^cin;
   assign cout = (temp_sum & cin) + (a & b);
endmodule

fulladder_tb.v
module full_adder_tb;
       wire sum, cout;
       reg a, b, cin;
       full_adder A1(sum, cout, a, b, cin);
       initial begin
           $dumpfile("sample.vcd");
           $dumpvars(0,full_adder_tb);
           $monitor($time, " a: %b, b: %b, cin: %b, sum: %b, cout: %b", a, b, cin, sum, cout);
           #2 a = 0; b =0; cin =0;
           #5 a = 0; b =0; cin =1;
           #5 a = 0; b =1; cin =0;
           #5 a = 0; b =1; cin =1;
           #5 a = 1; b =0; cin =0;
           #5 a = 1; b =0; cin =1;
           #5 a = 1; b =1; cin =0;
           #5 a = 1; b =1; cin =1;
           #40 $finish;
       end
endmodule

sample.vcd
$date
	Fri Dec 09 15:18:46 2022
$end
$version
	Icarus Verilog
$end
$timescale
	1s
$end
$scope module full_adder_tb $end
$var wire 1 ! sum $end
$var wire 1 " cout $end
$var reg 1 # a $end
$var reg 1 $ b $end
$var reg 1 % cin $end
$scope module A1 $end
$var wire 1 # a $end
$var wire 1 $ b $end
$var wire 1 % cin $end
$var wire 1 ! sum $end
$var wire 1 & temp_sum $end
$var wire 1 " cout $end
$upscope $end
$upscope $end
$enddefinitions $end
$comment Show the parameter values. $end
$dumpall
$end
#0
$dumpvars
x&
x%
x$
x#
x"
x!
$end
#2
0!
0"
0&
0%
0$
0#
#7
1!
1%
#12
1&
0%
1$
#17
0!
1"
1%
#22
1!
0"
0%
0$
1#
#27
0!
1"
1%
#32
0&
1"
0%
1$
#37
1!
1%
