srFF.v
module srFF(s,r,q,rst,qbar,clk);
input s,r,clk,rst;
output reg q,qbar;
always@(posedge clk or posedge rst)
   if (rst)
   begin
       q<=1'b0;
       qbar<=1'b1;
   end
 else begin
case({s,r})
{1'b0,1'b0}: begin q<=q;qbar<=qbar; end
{1'b0,1'b1}: begin q<=1'b0;qbar<=1'b1; end
{1'b1,1'b0}: begin q<=1'b1;qbar<=1'b0; end
{1'b1,1'b1}: begin q<=1'bx; qbar<=1'bx; end
endcase
end
endmodule

srFFTest.v
module testbench;
reg clk;
reg rst;
reg s,r;
wire q;
wire qbar;
srFF sr_dut( .clk(clk), .rst(rst), .s(s), .r(r), .q(q), .qbar(qbar) );
initial begin
 $dumpfile ("srFFTest.vcd");
 $dumpvars (0, testbench);
 $monitor(" clk=  ",clk," s= ",s," r= " ,r," q= ", q," qbar= ",qbar," rst= ",rst);
   $dumpfile ("srFFTest.vcd");
   $dumpvars (0, testbench);
s = 1'b0;
r = 1'b0;
rst = 1;
clk=1;
#10
rst=0;
s=1'b1;
r=1'b0;
#10
rst=0;
s=1'b0;
r=1'b1;
#10
rst=0;
s=1'b1;
r=1'b1;
#10
rst=0;
s=1'b0;
r=1'b0;
#10
rst=1;
s=1'b1;
r=1'b0;
 
#10 $finish;
end
always #8 clk = ~clk;
endmodule

srFFTest.vcd
$date
	Fri Dec 09 16:30:13 2022
$end
$version
	Icarus Verilog
$end
$timescale
	1s
$end
$scope module testbench $end
$var wire 1 ! qbar $end
$var wire 1 " q $end
$var reg 1 # clk $end
$var reg 1 $ r $end
$var reg 1 % rst $end
$var reg 1 & s $end
$scope module sr_dut $end
$var wire 1 # clk $end
$var wire 1 $ r $end
$var wire 1 % rst $end
$var wire 1 & s $end
$var reg 1 " q $end
$var reg 1 ! qbar $end
$upscope $end
$upscope $end
$scope module testbench $end
$scope module sr_dut $end
$upscope $end
$upscope $end
$enddefinitions $end
$comment Show the parameter values. $end
$dumpall
$end
#0
$dumpvars
0&
1%
0$
1#
0"
1!
$end
#8
0#
#10
1&
0%
#16
0!
1"
1#
#20
1$
0&
#24
0#
#30
1&
#32
x!
x"
1#
#40
0#
0$
0&
#48
1#
#50
1!
0"
1&
1%
